bp_fabric_search/__init__.py
bp_fabric_search/entrypoint.py
bp_fabric_search/helpers/__init__.py
bp_fabric_search/helpers/apic.py
bp_fabric_search/helpers/config.py
bp_fabric_search/helpers/logging.py
bp_fabric_search/helpers/printer.py
bp_fabric_search/inventory/__init__.py
bp_fabric_search/inventory/inventory.py
bp_fabric_search-0.1.3.dist-info/LICENSE.txt
bp_fabric_search-0.1.3.dist-info/METADATA
bp_fabric_search-0.1.3.dist-info/WHEEL
bp_fabric_search-0.1.3.dist-info/entry_points.txt
bp_fabric_search-0.1.3.dist-info/RECORD
