Metadata-Version: 2.1
Name: bp-fabric-search
Version: 0.1.3
Summary: Python based search utility to query multiple Cisco ACI fabrics at once.
Author: Fraser Henshaw
Author-email: fraser@bestpath.io
Requires-Python: >=3.9.5,<4.0.0
Classifier: Programming Language :: Python :: 3
Classifier: Programming Language :: Python :: 3.10
Classifier: Programming Language :: Python :: 3.11
Classifier: Programming Language :: Python :: 3.12
Requires-Dist: httpx (>=0.25.2,<0.26.0)
Requires-Dist: prettytable (>=3.9.0,<4.0.0)
Requires-Dist: pydantic (>=2.5.2,<3.0.0)
Requires-Dist: python-dotenv (>=1.0.0,<2.0.0)
Requires-Dist: pyyaml (>=6.0.1,<7.0.0)
Requires-Dist: urllib3 (>=2.1.0,<3.0.0)
